odoo/addons/event_sale_reservation/README.rst
odoo/addons/event_sale_reservation/__init__.py
odoo/addons/event_sale_reservation/__manifest__.py
odoo/addons/event_sale_reservation/exceptions.py
odoo/addons/event_sale_reservation/i18n/es.po
odoo/addons/event_sale_reservation/i18n/event_sale_reservation.pot
odoo/addons/event_sale_reservation/i18n/it.po
odoo/addons/event_sale_reservation/models/__init__.py
odoo/addons/event_sale_reservation/models/event_type.py
odoo/addons/event_sale_reservation/models/product_template.py
odoo/addons/event_sale_reservation/models/sale_order.py
odoo/addons/event_sale_reservation/models/sale_order_line.py
odoo/addons/event_sale_reservation/readme/CONFIGURE.md
odoo/addons/event_sale_reservation/readme/CONTRIBUTORS.md
odoo/addons/event_sale_reservation/readme/DESCRIPTION.md
odoo/addons/event_sale_reservation/readme/ROADMAP.md
odoo/addons/event_sale_reservation/readme/USAGE.md
odoo/addons/event_sale_reservation/reports/__init__.py
odoo/addons/event_sale_reservation/reports/sale_report.py
odoo/addons/event_sale_reservation/reports/sale_report_view.xml
odoo/addons/event_sale_reservation/static/description/icon.png
odoo/addons/event_sale_reservation/static/description/index.html
odoo/addons/event_sale_reservation/tests/__init__.py
odoo/addons/event_sale_reservation/tests/test_event_sale.py
odoo/addons/event_sale_reservation/views/event_type_view.xml
odoo/addons/event_sale_reservation/views/product_template_view.xml
odoo/addons/event_sale_reservation/views/sale_order_view.xml
odoo/addons/event_sale_reservation/wizards/__init__.py
odoo/addons/event_sale_reservation/wizards/registration_editor.py
odoo/addons/event_sale_reservation/wizards/registration_editor_line.py
odoo/addons/event_sale_reservation/wizards/registration_editor_view.xml
odoo_addon_event_sale_reservation-17.0.1.0.2.dist-info/METADATA
odoo_addon_event_sale_reservation-17.0.1.0.2.dist-info/WHEEL
odoo_addon_event_sale_reservation-17.0.1.0.2.dist-info/top_level.txt
odoo_addon_event_sale_reservation-17.0.1.0.2.dist-info/RECORD
