Metadata-Version: 2.1
Name: odoo-addon-event_sale_reservation
Version: 17.0.1.0.2
Requires-Python: >=3.10
Requires-Dist: odoo>=17.0a,<17.1dev
Summary: Allow selling event registrations before the event exists
Home-page: https://github.com/OCA/event
License: AGPL-3
Author: Tecnativa, Odoo Community Association (OCA)
Author-email: support@odoo-community.org
Classifier: Programming Language :: Python
Classifier: Framework :: Odoo
Classifier: Framework :: Odoo :: 17.0
Classifier: License :: OSI Approved :: GNU Affero General Public License v3
Classifier: Development Status :: 6 - Mature
